[
  { "id": "leaderdance", "title": "LeaderDance — Школа танцев", "image": "assets/images/leaderdance.jpg", "rarity": "редкий", "weight": 30 },
  { "id": "kutum", "title": "Кутум", "image": "assets/images/kutum.jpg", "rarity": "обычный", "weight": 60 },
  { "id": "yafunk", "title": "Yafunk — Дом танца", "image": "assets/images/yafunk.jpg", "rarity": "редкий", "weight": 30 },
  { "id": "dost", "title": "DOST", "image": "assets/images/dost.jpg", "rarity": "редкий", "weight": 30 },
  { "id": "vkusno", "title": "Вкусно и Точка", "image": "assets/images/vkusno.jpg", "rarity": "редкий", "weight": 30 },
  { "id": "akula", "title": "Akula — Магазин кроссовок", "image": "assets/images/akula.jpg", "rarity": "редкий", "weight": 30 },
  { "id": "akulafood", "title": "Akula.food — Кафе", "image": "assets/images/akulafood.jpg", "rarity": "обычный", "weight": 60 },
  { "id": "bar718", "title": "Бар 718", "image": "assets/images/bar718.jpg", "rarity": "обычный", "weight": 60 },
  { "id": "lenina", "title": "Улица Ленина", "image": "assets/images/lenina.jpg", "rarity": "обычный", "weight": 60 },
  { "id": "pobedy", "title": "Улица Победы", "image": "assets/images/pobedy.jpg", "rarity": "обычный", "weight": 60 },
  { "id": "yarmarka", "title": "ТЦ Ярмарка", "image": "assets/images/yarmarka.jpg", "rarity": "редкий", "weight": 30 },
  { "id": "alimpik", "title": "ТЦ Алимпик", "image": "assets/images/alimpik.jpg", "rarity": "редкий", "weight": 30 },
  { "id": "tatarbazar", "title": "Татар-Базар — рынок", "image": "assets/images/tatarbazar.jpg", "rarity": "обычный", "weight": 60 },
  { "id": "vastorg", "title": "ТЦ Васторг", "image": "assets/images/vastorg.jpg", "rarity": "обычный", "weight": 60 },
  { "id": "gosty", "title": "Gosty — Кофейня", "image": "assets/images/gosty.jpg", "rarity": "редкий", "weight": 30 },
  { "id": "tricats", "title": "ТЦ Три кота", "image": "assets/images/tricats.jpg", "rarity": "редкий", "weight": 30 },
  { "id": "astr-vokzal", "title": "Астраханский вокзал", "image": "assets/images/astr-vokzal.jpg", "rarity": "обычный", "weight": 60 },
  { "id": "jd-vokzal", "title": "ЖД Вокзал", "image": "assets/images/jd-vokzal.jpg", "rarity": "обычный", "weight": 60 },
  { "id": "arkadia", "title": "Парк Аркадия", "image": "assets/images/arkadia.jpg", "rarity": "обычный", "weight": 60 },
  { "id": "opera", "title": "Театр Оперы и Балета", "image": "assets/images/opera.jpg", "rarity": "редкий", "weight": 30 },
  { "id": "novy-most", "title": "Новый Мост", "image": "assets/images/novy-most.jpg", "rarity": "обычный", "weight": 60 },
  { "id": "pistachio", "title": "Golden Pistachio / Гранд Отель", "image": "assets/images/pistachio.jpg", "rarity": "легендарный", "weight": 5 },
  { "id": "vedomstvo", "title": "Астраханское биржевое ведомство — Достопримечательность", "image": "assets/images/vedomstvo.jpg", "rarity": "легендарный", "weight": 5 },
  { "id": "lebed", "title": "Лебединый домик — Достопримечательность", "image": "assets/images/lebed.jpg", "rarity": "легендарный", "weight": 5 },
  { "id": "stary-most", "title": "Старый мост", "image": "assets/images/stary-most.jpg", "rarity": "обычный", "weight": 60 },
  { "id": "myaso-most", "title": "Мясокомбинатский мост", "image": "assets/images/myaso-most.jpg", "rarity": "обычный", "weight": 60 },
  { "id": "pristan17", "title": "17-я пристань", "image": "assets/images/pristan17.jpg", "rarity": "редкий", "weight": 30 },
  { "id": "sobor-vladimir", "title": "Собор Святого Владимира — Православный храм", "image": "assets/images/sobor-vladimir.jpg", "rarity": "легендарный", "weight": 5 },
  { "id": "triump", "title": "Триумфальная Арка — Достопримечательность", "image": "assets/images/triump.jpg", "rarity": "легендарный", "weight": 5 },
  { "id": "kremlin", "title": "Астраханский Кремль", "image": "assets/images/kremlin.jpg", "rarity": "супер-редкий", "weight": 1 }
]
